{
  "name": "idstack",
  "version": "2.5.0.0",
  "description": "Evidence-based instructional design pipeline. 11 skills for needs analysis, learning objectives, assessment design, course building, quality review, accessibility audit, red team, and LMS export.",
  "author": "Philippos Savvides",
  "homepage": "https://idstack.org",
  "repository": "https://github.com/savvides/idstack",
  "license": "MIT",
  "plugins": [
    {
      "name": "idstack",
      "description": "All 11 idstack skills as a single Codex plugin.",
      "skills_dir": "dist/codex/skills"
    }
  ]
}
